README.rst
setup.py
djorm_ext_pool.egg-info/PKG-INFO
djorm_ext_pool.egg-info/SOURCES.txt
djorm_ext_pool.egg-info/dependency_links.txt
djorm_ext_pool.egg-info/not-zip-safe
djorm_ext_pool.egg-info/requires.txt
djorm_ext_pool.egg-info/top_level.txt
djorm_pool/__init__.py