Metadata-Version: 1.1
Name: djorm-ext-pool
Version: 0.8
Summary: DB-API2 connection pool for Django (for postgresql, mysql and sqlite)
Home-page: https://github.com/niwibe/djorm-ext-pool
Author: Andrey Antukh
Author-email: niwi@niwi.be
License: BSD
Platform: OS Independent
Classifier: Development Status :: 5 - Production/Stable
Classifier: Framework :: Django
Classifier: Intended Audience :: Developers
Classifier: License :: OSI Approved :: BSD License
Classifier: Operating System :: OS Independent
Classifier: Programming Language :: Python
Classifier: Topic :: Internet :: WWW/HTTP
